symengine/functions.py
symengine/test_utilities.py
symengine/__init__.py
symengine/sympy_compat.py
symengine/utilities.py
symengine/printing.py
symengine/tests/test_lambdify.py
symengine/tests/test_sage.py
symengine/tests/test_sympy_compat.py
symengine/tests/test_solve.py
symengine/tests/test_subs.py
symengine/tests/__init__.py
symengine/tests/test_matrices.py
symengine/tests/test_series_expansion.py
symengine/tests/test_sympy_conv.py
symengine/tests/test_cse.py
symengine/tests/test_arit.py
symengine/tests/test_pickling.py
symengine/tests/test_printing.py
symengine/tests/test_functions.py
symengine/tests/test_dict_basic.py
symengine/tests/test_var.py
symengine/tests/test_expr.py
symengine/tests/test_number.py
symengine/tests/test_sympify.py
symengine/tests/test_ntheory.py
symengine/tests/test_sets.py
symengine/tests/test_symbol.py
symengine/tests/test_logic.py
symengine/tests/test_eval.py
symengine/tests/__pycache__/test_symbol.cpython-310.pyc
symengine/tests/__pycache__/test_sympify.cpython-310.pyc
symengine/tests/__pycache__/test_matrices.cpython-310.pyc
symengine/tests/__pycache__/test_eval.cpython-310.pyc
symengine/tests/__pycache__/test_series_expansion.cpython-310.pyc
symengine/tests/__pycache__/test_var.cpython-310.pyc
symengine/tests/__pycache__/test_logic.cpython-310.pyc
symengine/tests/__pycache__/test_dict_basic.cpython-310.pyc
symengine/tests/__pycache__/test_lambdify.cpython-310.pyc
symengine/tests/__pycache__/test_number.cpython-310.pyc
symengine/tests/__pycache__/test_ntheory.cpython-310.pyc
symengine/tests/__pycache__/test_expr.cpython-310.pyc
symengine/tests/__pycache__/test_printing.cpython-310.pyc
symengine/tests/__pycache__/test_functions.cpython-310.pyc
symengine/tests/__pycache__/test_subs.cpython-310.pyc
symengine/tests/__pycache__/test_solve.cpython-310.pyc
symengine/tests/__pycache__/test_pickling.cpython-310.pyc
symengine/tests/__pycache__/test_sets.cpython-310.pyc
symengine-0.14.1.dist-info/RECORD
symengine-0.14.1.dist-info/WHEEL
symengine-0.14.1.dist-info/top_level.txt
symengine-0.14.1.dist-info/METADATA
symengine-0.14.1.dist-info/licenses/LICENSE
symengine-0.14.1.dist-info/licenses/AUTHORS
